sanic_transmute/__init__.py
sanic_transmute/handler.py
sanic_transmute/route.py
sanic_transmute/swagger.py
tests/__init__.py
tests/conftest.py
tests/test_parsing.py
tests/test_route.py
tests/test_swagger.py
tests/utils.py
sanic_transmute-0.1.3.dist-info/LICENSE
sanic_transmute-0.1.3.dist-info/METADATA
sanic_transmute-0.1.3.dist-info/WHEEL
sanic_transmute-0.1.3.dist-info/top_level.txt
sanic_transmute-0.1.3.dist-info/RECORD
