Metadata-Version: 2.1
Name: sanic-transmute
Version: 0.1.3
Summary: UNKNOWN
Home-page: https://github.com/yunstanford/sanic-transmute/
Author: Yun Xu
Author-email: yunxu1992@gmail.com
License: UNKNOWN
Platform: UNKNOWN
Classifier: Development Status :: 5 - Production/Stable
Classifier: Operating System :: MacOS
Classifier: Operating System :: POSIX :: Linux
Classifier: Topic :: System :: Software Distribution
Classifier: License :: OSI Approved :: MIT License
Classifier: Programming Language :: Python
Classifier: Programming Language :: Python :: 3
Classifier: Programming Language :: Python :: 3.5
Classifier: Programming Language :: Python :: 3.6
Classifier: Programming Language :: Python :: 3.7
Requires-Dist: transmute-core (>=1.9)
Requires-Dist: sanic
